Metadata-Version: 2.1
Name: pycachedb
Version: 0.3.2
Summary: PyCacheDB is a smallest embedded kay-value caching library.
Home-page: https://github.com/superoutput/pycachedb
Author: Savage Lasa
Author-email: superoutput@gmail.com
License: Savage
Keywords: python cache caching cached embedded database db
Platform: UNKNOWN
